bytesized/__init__.py
bytesized/bytesized.py
bytesized-0.1.1.dist-info/LICENSE
bytesized-0.1.1.dist-info/METADATA
bytesized-0.1.1.dist-info/WHEEL
bytesized-0.1.1.dist-info/top_level.txt
bytesized-0.1.1.dist-info/RECORD
