Metadata-Version: 2.1
Name: bytesized
Version: 0.1.1
Summary: Convert all of your bytes
Home-page: https://github.com/kcalmwinds/dataconverter
Author: Mark J Cameron
Author-email: kcalmwinds@gmail.com
License: UNKNOWN
Platform: UNKNOWN
Classifier: Programming Language :: Python :: 3
Classifier: License :: OSI Approved :: GNU Library or Lesser General Public License (LGPL)
Classifier: Operating System :: OS Independent
Requires-Python: >=3.6
